{"nm":"Composition","ddd":0,"h":500,"w":500,"meta":{"g":"@lottiefiles/toolkit-js 0.33.2"},"layers":[{"ty":3,"nm":"Main Stroke width - Color Ctrl","sr":1,"st":0,"op":143,"ip":0,"hd":false,"ddd":0,"bm":0,"hasMask":false,"ao":0,"ks":{"a":{"a":0,"k":[50,50,0],"ix":1},"s":{"a":0,"k":[100,100,100],"ix":6},"sk":{"a":0,"k":0},"p":{"a":0,"k":[0,0,0],"ix":2},"r":{"a":0,"k":0,"ix":10},"sa":{"a":0,"k":0},"o":{"a":0,"k":0,"ix":11}},"ef":[{"ty":5,"mn":"ADBE Slider Control","nm":"Stroke width","ix":1,"en":1,"ef":[{"ty":0,"mn":"ADBE Slider Control-0001","nm":"Deslizador","ix":1,"v":{"a":0,"k":16,"ix":1}}]},{"ty":5,"mn":"ADBE Color Control","nm":"Base Color","ix":2,"en":1,"ef":[{"ty":2,"mn":"ADBE Color Control-0001","nm":"Color","ix":1,"v":{"a":0,"k":[0.251,0.251,0.251],"ix":1}}]},{"ty":5,"mn":"ADBE Color Control","nm":"Highlight","ix":3,"en":1,"ef":[{"ty":2,"mn":"ADBE Color Control-0001","nm":"Color","ix":1,"v":{"a":0,"k":[0.2314,0.5098,0.9647],"ix":1}}]},{"ty":5,"mn":"ADBE Color Control","nm":"Shadow","ix":4,"en":1,"ef":[{"ty":2,"mn":"ADBE Color Control-0001","nm":"Color","ix":1,"v":{"a":0,"k":[0.9412,0.8863,0.2549],"ix":1}}]}],"ind":1,"parent":8},{"ty":4,"nm":"QR","sr":1,"st":0,"op":143,"ip":0,"hd":false,"ddd":0,"bm":0,"hasMask":false,"ao":0,"ks":{"a":{"a":0,"k":[250,328.749,0],"ix":1},"s":{"a":0,"k":[100,100,100],"ix":6},"sk":{"a":0,"k":0},"p":{"a":0,"k":[104.249,49.998,0],"ix":2},"r":{"a":0,"k":0,"ix":10,"x":"var $bm_rt;\n$bm_rt = $bm_mul(thisComp.layer('Phone').transform.rotation, -1);"},"sa":{"a":0,"k":0},"o":{"a":0,"k":100,"ix":11}},"ef":[],"shapes":[{"ty":"gr","bm":0,"hd":false,"mn":"ADBE Vector Group","nm":"QR_B","ix":1,"cix":2,"np":2,"it":[{"ty":"gr","bm":0,"hd":false,"mn":"ADBE Vector Group","nm":"Ctrl","ix":1,"cix":2,"np":7,"it":[{"ty":"sh","bm":0,"hd":false,"mn":"ADBE Vector Shape - Group","nm":"Trazado 1","ix":1,"d":1,"ks":{"a":0,"k":{"c":true,"i":[[0,0],[0,0],[0,0],[0,0]],"o":[[0,0],[0,0],[0,0],[0,0]],"v":[[251.75,390],[311.251,390],[311.251,330.5],[251.75,330.5]]},"ix":2}},{"ty":"sh","bm":0,"hd":false,"mn":"ADBE Vector Shape - Group","nm":"Trazado 2","ix":2,"d":1,"ks":{"a":0,"k":{"c":false,"i":[[0,0],[0,0],[0,0]],"o":[[0,0],[0,0],[0,0]],"v":[[311.251,298.999],[251.75,298.999],[251.75,267.499]]},"ix":2}},{"ty":"sh","bm":0,"hd":false,"mn":"ADBE Vector Shape - Group","nm":"Trazado 3","ix":3,"d":1,"ks":{"a":0,"k":{"c":false,"i":[[0,0],[0,0]],"o":[[0,0],[0,0]],"v":[[283.25,267.499],[311.251,267.499]]},"ix":2}},{"ty":"sh","bm":0,"hd":false,"mn":"ADBE Vector Shape - Group","nm":"Trazado 5","ix":4,"d":1,"ks":{"a":0,"k":{"c":false,"i":[[0,0],[0,0]],"o":[[0,0],[0,0]],"v":[[188.75,390],[188.75,362]]},"ix":2}},{"ty":"sh","bm":0,"hd":false,"mn":"ADBE Vector Shape - Group","nm":"Trazado 4","ix":5,"d":1,"ks":{"a":0,"k":{"c":true,"i":[[0,0],[0,0],[0,0],[0,0]],"o":[[0,0],[0,0],[0,0],[0,0]],"v":[[188.749,267.499],[220.249,267.499],[220.249,298.999],[188.749,298.999]]},"ix":2}},{"ty":"sh","bm":0,"hd":false,"mn":"ADBE Vector Shape - Group","nm":"Trazado 6","ix":6,"d":1,"ks":{"a":0,"k":{"c":false,"i":[[0,0],[0,0],[0,0]],"o":[[0,0],[0,0],[0,0]],"v":[[188.75,330.499],[220.249,330.499],[220.249,390]]},"ix":2}},{"ty":"tm","bm":0,"hd":false,"mn":"ADBE Vector Filter - Trim","nm":"Recortar trazados 1","ix":7,"e":{"a":1,"k":[{"o":{"x":0.333,"y":0},"i":{"x":0.667,"y":1},"s":[0],"t":30},{"o":{"x":0.333,"y":0},"i":{"x":0.667,"y":1},"s":[100],"t":60},{"o":{"x":0.333,"y":0},"i":{"x":0.667,"y":1},"s":[100],"t":90},{"s":[0],"t":130}],"ix":2},"o":{"a":0,"k":0,"ix":3},"s":{"a":0,"k":0,"ix":1},"m":1},{"ty":"tr","a":{"a":0,"k":[250,328.749],"ix":1},"s":{"a":0,"k":[100,100],"ix":3,"x":"var $bm_rt;\n$bm_rt = content('Square').content('Square_Ctrl').transform.scale;"},"sk":{"a":0,"k":0,"ix":4},"p":{"a":0,"k":[250,328.749],"ix":2},"r":{"a":0,"k":0,"ix":6},"sa":{"a":0,"k":0,"ix":5},"o":{"a":0,"k":100,"ix":7}}]},{"ty":"st","bm":0,"hd":false,"mn":"ADBE Vector Graphic - Stroke","nm":"Stroke Base","lc":2,"lj":2,"ml":1,"o":{"a":0,"k":100,"ix":4},"w":{"a":0,"k":16,"ix":5,"x":"var $bm_rt;\n$bm_rt = $bm_sum(thisComp.layer('Main Stroke width - Color Ctrl').effect('Stroke width')('ADBE Slider Control-0001'), 2);"},"c":{"a":0,"k":[0.2314,0.5098,0.9647],"ix":3,"x":"var $bm_rt;\n$bm_rt = thisComp.layer('Main Stroke width - Color Ctrl').effect('Base Color')('ADBE Color Control-0001');"}},{"ty":"tr","a":{"a":0,"k":[250,328.749],"ix":1},"s":{"a":0,"k":[100,100],"ix":3},"sk":{"a":0,"k":0,"ix":4},"p":{"a":0,"k":[250,328.749],"ix":2},"r":{"a":0,"k":0,"ix":6},"sa":{"a":0,"k":0,"ix":5},"o":{"a":0,"k":100,"ix":7}}]},{"ty":"gr","bm":0,"hd":false,"mn":"ADBE Vector Group","nm":"QR_H","ix":2,"cix":2,"np":2,"it":[{"ty":"gr","bm":0,"hd":false,"mn":"ADBE Vector Group","nm":"Ctrl","ix":1,"cix":2,"np":6,"it":[{"ty":"sh","bm":0,"hd":false,"mn":"ADBE Vector Shape - Group","nm":"Trazado 1","ix":1,"d":1,"ks":{"a":0,"k":{"c":true,"i":[[0,0],[0,0],[0,0],[0,0]],"o":[[0,0],[0,0],[0,0],[0,0]],"v":[[251.75,390],[311.251,390],[311.251,330.5],[251.75,330.5]]},"ix":2}},{"ty":"sh","bm":0,"hd":false,"mn":"ADBE Vector Shape - Group","nm":"Trazado 2","ix":2,"d":1,"ks":{"a":0,"k":{"c":false,"i":[[0,0],[0,0],[0,0]],"o":[[0,0],[0,0],[0,0]],"v":[[311.251,298.999],[251.75,298.999],[251.75,267.499]]},"ix":2}},{"ty":"sh","bm":0,"hd":false,"mn":"ADBE Vector Shape - Group","nm":"Trazado 3","ix":3,"d":1,"ks":{"a":0,"k":{"c":false,"i":[[0,0],[0,0]],"o":[[0,0],[0,0]],"v":[[283.25,267.499],[311.251,267.499]]},"ix":2}},{"ty":"sh","bm":0,"hd":false,"mn":"ADBE Vector Shape - Group","nm":"Trazado 5","ix":4,"d":1,"ks":{"a":0,"k":{"c":false,"i":[[0,0],[0,0]],"o":[[0,0],[0,0]],"v":[[188.75,390],[188.75,362]]},"ix":2}},{"ty":"sh","bm":0,"hd":false,"mn":"ADBE Vector Shape - Group","nm":"Trazado 4","ix":5,"d":1,"ks":{"a":0,"k":{"c":true,"i":[[0,0],[0,0],[0,0],[0,0]],"o":[[0,0],[0,0],[0,0],[0,0]],"v":[[188.749,267.499],[220.249,267.499],[220.249,298.999],[188.749,298.999]]},"ix":2}},{"ty":"sh","bm":0,"hd":false,"mn":"ADBE Vector Shape - Group","nm":"Trazado 6","ix":6,"d":1,"ks":{"a":0,"k":{"c":false,"i":[[0,0],[0,0],[0,0]],"o":[[0,0],[0,0],[0,0]],"v":[[188.75,330.499],[220.249,330.499],[220.249,390]]},"ix":2}},{"ty":"tr","a":{"a":0,"k":[250,328.749],"ix":1},"s":{"a":0,"k":[100,100],"ix":3},"sk":{"a":0,"k":0,"ix":4},"p":{"a":0,"k":[250,328.749],"ix":2},"r":{"a":0,"k":0,"ix":6},"sa":{"a":0,"k":0,"ix":5},"o":{"a":0,"k":100,"ix":7}}]},{"ty":"st","bm":0,"hd":false,"mn":"ADBE Vector Graphic - Stroke","nm":"Stroke Highlight","lc":2,"lj":2,"ml":1,"o":{"a":0,"k":100,"ix":4},"w":{"a":0,"k":16,"ix":5,"x":"var $bm_rt;\n$bm_rt = thisComp.layer('Main Stroke width - Color Ctrl').effect('Stroke width')('ADBE Slider Control-0001');"},"c":{"a":0,"k":[0.2314,0.5098,0.9647],"ix":3,"x":"var $bm_rt;\n$bm_rt = thisComp.layer('Main Stroke width - Color Ctrl').effect('Highlight')('ADBE Color Control-0001');"}},{"ty":"tr","a":{"a":0,"k":[250,328.749],"ix":1},"s":{"a":0,"k":[100,100],"ix":3,"x":"var $bm_rt;\n$bm_rt = content('Square').content('Square_Ctrl').transform.scale;"},"sk":{"a":0,"k":0,"ix":4},"p":{"a":0,"k":[250,328.749],"ix":2},"r":{"a":0,"k":0,"ix":6},"sa":{"a":0,"k":0,"ix":5},"o":{"a":0,"k":100,"ix":7}}]},{"ty":"gr","bm":0,"hd":false,"mn":"ADBE Vector Group","nm":"Square_Stroke","ix":3,"cix":2,"np":2,"it":[{"ty":"gr","bm":0,"hd":false,"mn":"ADBE Vector Group","nm":"Square_Ctrl","ix":1,"cix":2,"np":1,"it":[{"ty":"sh","bm":0,"hd":false,"mn":"ADBE Vector Shape - Group","nm":"Trazado 1","ix":1,"d":1,"ks":{"a":0,"k":{"c":true,"i":[[0,0],[0,0],[0,0],[0,0]],"o":[[0,0],[0,0],[0,0],[0,0]],"v":[[-92.75,92.75],[92.75,92.75],[92.75,-92.75],[-92.75,-92.75]]},"ix":2}},{"ty":"tr","a":{"a":0,"k":[0,0],"ix":1},"s":{"a":1,"k":[{"o":{"x":0.67,"y":-0.306},"i":{"x":0.667,"y":1},"s":[100,100],"t":55},{"o":{"x":0.497,"y":0},"i":{"x":0.547,"y":1},"s":[80,80],"t":60},{"o":{"x":0.555,"y":0},"i":{"x":0.563,"y":1},"s":[120,120],"t":75},{"o":{"x":0.333,"y":0},"i":{"x":0.637,"y":1.886},"s":[90,90],"t":85},{"s":[100,100],"t":95}],"ix":3},"sk":{"a":0,"k":0,"ix":4},"p":{"a":0,"k":[250,328.749],"ix":2},"r":{"a":0,"k":0,"ix":6},"sa":{"a":0,"k":0,"ix":5},"o":{"a":0,"k":100,"ix":7}}]},{"ty":"st","bm":0,"hd":false,"mn":"ADBE Vector Graphic - Stroke","nm":"Stroke Base","lc":2,"lj":2,"ml":1,"o":{"a":0,"k":100,"ix":4},"w":{"a":0,"k":16,"ix":5,"x":"var $bm_rt;\n$bm_rt = thisComp.layer('Main Stroke width - Color Ctrl').effect('Stroke width')('ADBE Slider Control-0001');"},"c":{"a":0,"k":[0.2314,0.5098,0.9647],"ix":3,"x":"var $bm_rt;\n$bm_rt = thisComp.layer('Main Stroke width - Color Ctrl').effect('Base Color')('ADBE Color Control-0001');"}},{"ty":"tr","a":{"a":0,"k":[250,328.749],"ix":1},"s":{"a":0,"k":[100,100],"ix":3},"sk":{"a":0,"k":0,"ix":4},"p":{"a":0,"k":[250,328.749],"ix":2},"r":{"a":0,"k":0,"ix":6},"sa":{"a":0,"k":0,"ix":5},"o":{"a":0,"k":100,"ix":7}}]},{"ty":"gr","bm":0,"hd":false,"mn":"ADBE Vector Group","nm":"Scan","ix":4,"cix":2,"np":2,"it":[{"ty":"sh","bm":0,"hd":false,"mn":"ADBE Vector Shape - Group","nm":"Trazado 1","ix":1,"d":1,"ks":{"a":0,"k":{"c":false,"i":[[0,0],[0,0]],"o":[[0,0],[0,0]],"v":[[-92.75,0],[92.75,0]]},"ix":2}},{"ty":"st","bm":0,"hd":false,"mn":"ADBE Vector Graphic - Stroke","nm":"Stroke Highlight","lc":2,"lj":2,"ml":1,"o":{"a":1,"k":[{"o":{"x":0.167,"y":0.167},"i":{"x":0.833,"y":0.833},"s":[0],"t":0},{"o":{"x":0.167,"y":0.167},"i":{"x":0.833,"y":0.833},"s":[100],"t":1},{"o":{"x":0.167,"y":0.167},"i":{"x":0.833,"y":0.833},"s":[100],"t":57},{"s":[0],"t":58}],"ix":4},"w":{"a":0,"k":16,"ix":5,"x":"var $bm_rt;\n$bm_rt = thisComp.layer('Main Stroke width - Color Ctrl').effect('Stroke width')('ADBE Slider Control-0001');"},"c":{"a":0,"k":[0.2314,0.5098,0.9647],"ix":3,"x":"var $bm_rt;\n$bm_rt = thisComp.layer('Main Stroke width - Color Ctrl').effect('Highlight')('ADBE Color Control-0001');"}},{"ty":"tr","a":{"a":0,"k":[0,0],"ix":1},"s":{"a":0,"k":[100,100],"ix":3},"sk":{"a":0,"k":0,"ix":4},"p":{"a":1,"k":[{"o":{"x":0.61,"y":0},"i":{"x":0.4,"y":1},"s":[250,420.758],"t":0,"ti":[0,0],"to":[0,-28]},{"o":{"x":0.61,"y":0},"i":{"x":0.4,"y":1},"s":[250,252.758],"t":30,"ti":[0,-28],"to":[0,0]},{"s":[250,420.758],"t":60}],"ix":2},"r":{"a":0,"k":0,"ix":6},"sa":{"a":0,"k":0,"ix":5},"o":{"a":0,"k":100,"ix":7}}]},{"ty":"gr","bm":0,"hd":false,"mn":"ADBE Vector Group","nm":"Square","ix":5,"cix":2,"np":2,"it":[{"ty":"gr","bm":0,"hd":false,"mn":"ADBE Vector Group","nm":"Square_Ctrl","ix":1,"cix":2,"np":1,"it":[{"ty":"sh","bm":0,"hd":false,"mn":"ADBE Vector Shape - Group","nm":"Trazado 1","ix":1,"d":1,"ks":{"a":0,"k":{"c":true,"i":[[0,0],[0,0],[0,0],[0,0]],"o":[[0,0],[0,0],[0,0],[0,0]],"v":[[-92.75,92.75],[92.75,92.75],[92.75,-92.75],[-92.75,-92.75]]},"ix":2}},{"ty":"tr","a":{"a":0,"k":[0,0],"ix":1},"s":{"a":1,"k":[{"o":{"x":0.67,"y":-0.306},"i":{"x":0.667,"y":1},"s":[100,100],"t":55},{"o":{"x":0.497,"y":0},"i":{"x":0.547,"y":1},"s":[80,80],"t":60},{"o":{"x":0.555,"y":0},"i":{"x":0.563,"y":1},"s":[120,120],"t":75},{"o":{"x":0.333,"y":0},"i":{"x":0.637,"y":1.886},"s":[90,90],"t":85},{"s":[100,100],"t":95}],"ix":3},"sk":{"a":0,"k":0,"ix":4},"p":{"a":0,"k":[250,328.749],"ix":2},"r":{"a":0,"k":0,"ix":6},"sa":{"a":0,"k":0,"ix":5},"o":{"a":0,"k":100,"ix":7}}]},{"ty":"fl","bm":0,"hd":false,"mn":"ADBE Vector Graphic - Fill","nm":"Relleno 1","c":{"a":0,"k":[1,1,1],"ix":4},"r":1,"o":{"a":0,"k":100,"ix":5}},{"ty":"tr","a":{"a":0,"k":[250,328.749],"ix":1},"s":{"a":0,"k":[100,100],"ix":3},"sk":{"a":0,"k":0,"ix":4},"p":{"a":0,"k":[250,328.749],"ix":2},"r":{"a":0,"k":0,"ix":6},"sa":{"a":0,"k":0,"ix":5},"o":{"a":0,"k":100,"ix":7}}]}],"ind":2,"parent":1},{"ty":4,"nm":"Phone_Line","sr":1,"st":0,"op":145,"ip":0,"hd":false,"ddd":0,"bm":0,"hasMask":false,"ao":0,"ks":{"a":{"a":0,"k":[204.5,386.498,0],"ix":1},"s":{"a":0,"k":[100,100,100],"ix":6},"sk":{"a":0,"k":0},"p":{"a":0,"k":[204.5,386.498,0],"ix":2},"r":{"a":0,"k":0,"ix":10},"sa":{"a":0,"k":0},"o":{"a":0,"k":100,"ix":11}},"ef":[],"shapes":[{"ty":"sh","bm":0,"hd":false,"mn":"ADBE Vector Shape - Group","nm":"Trazado 1","ix":1,"d":1,"ks":{"a":0,"k":{"c":false,"i":[[0,0],[0,0]],"o":[[0,0],[0,0]],"v":[[215,386.498],[194,386.498]]},"ix":2}},{"ty":"st","bm":0,"hd":false,"mn":"ADBE Vector Graphic - Stroke","nm":"Stroke Highlight","lc":2,"lj":2,"ml":1,"o":{"a":0,"k":100,"ix":4},"w":{"a":0,"k":16,"ix":5,"x":"var $bm_rt;\n$bm_rt = thisComp.layer('Main Stroke width - Color Ctrl').effect('Stroke width')('ADBE Slider Control-0001');"},"c":{"a":0,"k":[0.2314,0.5098,0.9647],"ix":3,"x":"var $bm_rt;\n$bm_rt = thisComp.layer('Main Stroke width - Color Ctrl').effect('Highlight')('ADBE Color Control-0001');"}}],"ind":3,"parent":4},{"ty":4,"nm":"Phone","sr":1,"st":0,"op":145,"ip":0,"hd":false,"ddd":0,"bm":0,"hasMask":false,"ao":0,"ks":{"a":{"a":0,"k":[204.5,249.998,0],"ix":1},"s":{"a":0,"k":[100,100,100],"ix":6},"sk":{"a":0,"k":0},"p":{"a":0,"k":[4.5,49.998,0],"ix":2},"r":{"a":1,"k":[{"o":{"x":0.404,"y":-0.386},"i":{"x":0.667,"y":1},"s":[0],"t":0},{"o":{"x":0.333,"y":0},"i":{"x":0.667,"y":1},"s":[8],"t":25},{"o":{"x":0.333,"y":0},"i":{"x":0.667,"y":1},"s":[-8],"t":50},{"o":{"x":0.333,"y":0},"i":{"x":0.667,"y":1},"s":[6],"t":70},{"o":{"x":0.333,"y":0},"i":{"x":0.667,"y":1},"s":[-4],"t":85},{"o":{"x":0.333,"y":0},"i":{"x":0.373,"y":1},"s":[2],"t":95},{"s":[0],"t":100}],"ix":10},"sa":{"a":0,"k":0},"o":{"a":0,"k":100,"ix":11}},"ef":[],"shapes":[{"ty":"sh","bm":0,"hd":false,"mn":"ADBE Vector Shape - Group","nm":"Trazado 2","ix":1,"d":1,"ks":{"a":0,"k":{"c":false,"i":[[0,0],[0,0],[9.625,0],[0,0],[0,9.625],[0,0]],"o":[[0,0],[0,9.625],[0,0],[-9.625,0],[0,0],[0,0]],"v":[[257,81.998],[257,95.998],[239.5,113.498],[169.499,113.498],[152,95.998],[152,81.998]]},"ix":2}},{"ty":"sh","bm":0,"hd":false,"mn":"ADBE Vector Shape - Group","nm":"Trazado 3","ix":2,"d":1,"ks":{"a":0,"k":{"c":false,"i":[[0,0],[0,0],[9.302,0],[0,0],[0,9.586],[0,0],[-9.304,0],[0,0],[0,-9.581],[0,0]],"o":[[0,0],[0,9.584],[0,0],[-9.304,0],[0,0],[0,-9.586],[0,0],[9.304,0],[0,0],[0,0]],"v":[[305.999,346.248],[305.999,404.069],[289.083,421.498],[119.917,421.498],[103,404.069],[103,95.927],[119.917,78.498],[289.083,78.498],[305.999,95.927],[305.71,346.446]]},"ix":2}},{"ty":"st","bm":0,"hd":false,"mn":"ADBE Vector Graphic - Stroke","nm":"Stroke Base","lc":2,"lj":2,"ml":1,"o":{"a":0,"k":100,"ix":4},"w":{"a":0,"k":16,"ix":5,"x":"var $bm_rt;\n$bm_rt = thisComp.layer('Main Stroke width - Color Ctrl').effect('Stroke width')('ADBE Slider Control-0001');"},"c":{"a":0,"k":[0.2314,0.5098,0.9647],"ix":3,"x":"var $bm_rt;\n$bm_rt = thisComp.layer('Main Stroke width - Color Ctrl').effect('Base Color')('ADBE Color Control-0001');"}}],"ind":4,"parent":1},{"ty":4,"nm":"Phone_Mask","sr":1,"st":0,"op":140,"ip":0,"hd":false,"ddd":0,"bm":0,"hasMask":false,"td":1,"ao":0,"ks":{"a":{"a":0,"k":[0,0,0],"ix":1},"s":{"a":0,"k":[100,100,100],"ix":6},"sk":{"a":0,"k":0},"p":{"a":0,"k":[204.5,250,0],"ix":2},"r":{"a":0,"k":0,"ix":10},"sa":{"a":0,"k":0},"o":{"a":0,"k":100,"ix":11}},"ef":[],"shapes":[{"ty":"gr","bm":0,"hd":false,"mn":"ADBE Vector Group","nm":"Grupo 1","ix":1,"cix":2,"np":2,"it":[{"ty":"sh","bm":0,"hd":false,"mn":"ADBE Vector Shape - Group","nm":"Trazado 1","ix":1,"d":1,"ks":{"a":0,"k":{"c":true,"i":[[0,-9.59],[0,0],[9.31,0],[0,0],[0,9.58],[0,0],[-9.31,0],[0,0],[0,0],[-9.63,0],[0,0],[0,9.62],[0,0],[0,0]],"o":[[0,0],[0,9.58],[0,0],[-9.31,0],[0,0],[0,-9.59],[0,0],[0,0],[0,9.62],[0,0],[9.62,0],[0,0],[0,0],[9.31,0]],"v":[[101.5,-154.07],[101.5,154.07],[84.58,171.5],[-84.58,171.5],[-101.5,154.07],[-101.5,-154.07],[-84.58,-171.5],[-52.5,-171.5],[-52.5,-154],[-35,-136.5],[35,-136.5],[52.5,-154],[52.5,-171.5],[84.58,-171.5]]},"ix":2}},{"ty":"fl","bm":0,"hd":false,"mn":"ADBE Vector Graphic - Fill","nm":"Relleno 1","c":{"a":0,"k":[0.9451,0.9451,0.9451],"ix":4},"r":1,"o":{"a":0,"k":100,"ix":5}},{"ty":"tr","a":{"a":0,"k":[0,0],"ix":1},"s":{"a":0,"k":[100,100],"ix":3},"sk":{"a":0,"k":0,"ix":4},"p":{"a":0,"k":[0,0],"ix":2},"r":{"a":0,"k":0,"ix":6},"sa":{"a":0,"k":0,"ix":5},"o":{"a":0,"k":100,"ix":7}}]}],"ind":5,"parent":7},{"ty":4,"nm":"QR_Shadow","sr":1,"st":0,"op":143,"ip":0,"hd":false,"ddd":0,"bm":0,"tt":1,"hasMask":false,"ao":0,"ks":{"a":{"a":0,"k":[250,328.749,0],"ix":1},"s":{"a":0,"k":[100,100,100],"ix":6},"sk":{"a":0,"k":0},"p":{"a":0,"k":[104.249,49.998,0],"ix":2},"r":{"a":0,"k":0,"ix":10,"x":"var $bm_rt;\n$bm_rt = $bm_mul(thisComp.layer('Phone').transform.rotation, -1);"},"sa":{"a":0,"k":0},"o":{"a":0,"k":100,"ix":11}},"ef":[],"shapes":[{"ty":"gr","bm":0,"hd":false,"mn":"ADBE Vector Group","nm":"Square_Stroke","ix":1,"cix":2,"np":2,"it":[{"ty":"gr","bm":0,"hd":false,"mn":"ADBE Vector Group","nm":"Square_Ctrl","ix":1,"cix":2,"np":1,"it":[{"ty":"sh","bm":0,"hd":false,"mn":"ADBE Vector Shape - Group","nm":"Trazado 1","ix":1,"d":1,"ks":{"a":0,"k":{"c":true,"i":[[0,0],[0,0],[0,0],[0,0]],"o":[[0,0],[0,0],[0,0],[0,0]],"v":[[-92.75,92.75],[92.75,92.75],[92.75,-92.75],[-92.75,-92.75]]},"ix":2}},{"ty":"tr","a":{"a":0,"k":[0,0],"ix":1},"s":{"a":0,"k":[100,100],"ix":3,"x":"var $bm_rt;\n$bm_rt = thisComp.layer('QR').content('Square_Stroke').content('Square_Ctrl').transform.scale;"},"sk":{"a":0,"k":0,"ix":4},"p":{"a":0,"k":[250,328.749],"ix":2},"r":{"a":0,"k":0,"ix":6},"sa":{"a":0,"k":0,"ix":5},"o":{"a":0,"k":100,"ix":7}}]},{"ty":"st","bm":0,"hd":false,"mn":"ADBE Vector Graphic - Stroke","nm":"Shadow","lc":2,"lj":2,"ml":1,"o":{"a":0,"k":100,"ix":4},"w":{"a":0,"k":16,"ix":5,"x":"var $bm_rt;\n$bm_rt = $bm_mul(thisComp.layer('Main Stroke width - Color Ctrl').effect('Stroke width')('ADBE Slider Control-0001'), 3.5);"},"c":{"a":0,"k":[0.9451,0.9451,0.9451],"ix":3}},{"ty":"tr","a":{"a":0,"k":[250,328.749],"ix":1},"s":{"a":0,"k":[100,100],"ix":3},"sk":{"a":0,"k":0,"ix":4},"p":{"a":0,"k":[250,328.749],"ix":2},"r":{"a":0,"k":0,"ix":6},"sa":{"a":0,"k":0,"ix":5},"o":{"a":0,"k":100,"ix":7}}]},{"ty":"gr","bm":0,"hd":false,"mn":"ADBE Vector Group","nm":"FIX","ix":2,"cix":2,"np":2,"it":[{"ty":"rc","bm":0,"hd":false,"mn":"ADBE Vector Shape - Rect","nm":"Trazado de rectángulo 1","d":1,"p":{"a":0,"k":[0,0],"ix":3},"r":{"a":0,"k":0,"ix":4},"s":{"a":0,"k":[253,253],"ix":2}},{"ty":"fl","bm":0,"hd":false,"mn":"ADBE Vector Graphic - Fill","nm":"Relleno 1","c":{"a":0,"k":[0.9451,0.9451,0.9451],"ix":4},"r":1,"o":{"a":0,"k":0,"ix":5}},{"ty":"tr","a":{"a":0,"k":[0,0],"ix":1},"s":{"a":0,"k":[100,100],"ix":3},"sk":{"a":0,"k":0,"ix":4},"p":{"a":0,"k":[254,324],"ix":2},"r":{"a":0,"k":0,"ix":6},"sa":{"a":0,"k":0,"ix":5},"o":{"a":0,"k":100,"ix":7}}]}],"ind":6,"parent":1},{"ty":4,"nm":"Phone_Fill","sr":1,"st":0,"op":145,"ip":0,"hd":false,"ddd":0,"bm":0,"hasMask":false,"ao":0,"ks":{"a":{"a":0,"k":[204.5,249.998,0],"ix":1},"s":{"a":0,"k":[100,100,100],"ix":6},"sk":{"a":0,"k":0},"p":{"a":0,"k":[204.5,249.998,0],"ix":2},"r":{"a":0,"k":0,"ix":10},"sa":{"a":0,"k":0},"o":{"a":0,"k":100,"ix":11}},"ef":[],"shapes":[{"ty":"gr","bm":0,"hd":false,"mn":"ADBE Vector Group","nm":"Grupo 1","ix":1,"cix":2,"np":2,"it":[{"ty":"sh","bm":0,"hd":false,"mn":"ADBE Vector Shape - Group","nm":"Trazado 1","ix":1,"d":1,"ks":{"a":0,"k":{"c":true,"i":[[0,0],[0,9.625],[0,0],[0,0],[0,0],[-9.625,0]],"o":[[9.625,0],[0,0],[0,0],[0,0],[0,9.625],[0,0]],"v":[[35,17.5],[52.5,0],[52.5,-17.5],[-52.5,-17.5],[-52.5,0],[-35,17.5]]},"ix":2}},{"ty":"fl","bm":0,"hd":false,"mn":"ADBE Vector Graphic - Fill","nm":"Relleno 1","c":{"a":0,"k":[0.1333,0.7725,0.3686],"ix":4},"r":1,"o":{"a":0,"k":100,"ix":5}},{"ty":"tr","a":{"a":0,"k":[0,0],"ix":1},"s":{"a":0,"k":[100,100],"ix":3},"sk":{"a":0,"k":0,"ix":4},"p":{"a":0,"k":[204.5,95.998],"ix":2},"r":{"a":0,"k":0,"ix":6},"sa":{"a":0,"k":0,"ix":5},"o":{"a":0,"k":100,"ix":7}}]},{"ty":"gr","bm":0,"hd":false,"mn":"ADBE Vector Group","nm":"Grupo 2","ix":2,"cix":2,"np":2,"it":[{"ty":"sh","bm":0,"hd":false,"mn":"ADBE Vector Shape - Group","nm":"Trazado 1","ix":1,"d":1,"ks":{"a":0,"k":{"c":true,"i":[[48.842,0],[0,-9.586],[0,0],[-9.304,0],[0,0],[0,9.586],[0,103.817],[9.304,0]],"o":[[-9.304,0],[0,0],[0,9.586],[0,0],[9.304,0],[0.001,-103.809],[0,-9.583],[-48.842,0]],"v":[[-84.583,-171.5],[-101.5,-154.071],[-101.5,154.071],[-84.583,171.5],[84.583,171.5],[101.499,154.071],[101.499,-154.071],[84.583,-171.5]]},"ix":2}},{"ty":"fl","bm":0,"hd":false,"mn":"ADBE Vector Graphic - Fill","nm":"Relleno 1","c":{"a":0,"k":[1,1,1],"ix":4},"r":1,"o":{"a":0,"k":100,"ix":5}},{"ty":"tr","a":{"a":0,"k":[0,0],"ix":1},"s":{"a":0,"k":[100,100],"ix":3},"sk":{"a":0,"k":0,"ix":4},"p":{"a":0,"k":[204.5,249.998],"ix":2},"r":{"a":0,"k":0,"ix":6},"sa":{"a":0,"k":0,"ix":5},"o":{"a":0,"k":100,"ix":7}}]}],"ind":7,"parent":4},{"ty":3,"nm":"Zero | troke width - Color Ctrl","sr":1,"st":0,"op":143,"ip":0,"hd":false,"ddd":0,"bm":0,"hasMask":false,"ao":0,"ks":{"a":{"a":0,"k":[0,0,0],"ix":1},"s":{"a":0,"k":[100,100,100],"ix":6},"sk":{"a":0,"k":0},"p":{"a":0,"k":[250,250,0],"ix":2},"r":{"a":0,"k":0,"ix":10},"sa":{"a":0,"k":0},"o":{"a":0,"k":0,"ix":11}},"ef":[],"ind":8}],"v":"5.7.5","fr":60,"op":140,"ip":0,"assets":[]}